{
  "WorkItem": {
    "AffectedComponent": {
      "Name": "",
      "DisplayName": ""
    },
    "ClosedComment": "",
    "ClosedDate": null,
    "CommentCount": 0,
    "Custom": null,
    "Description": "I try to open a Outlook 2010 PST file with the SDK but get an exception. Does the SDK supports Outlook 2010 and 2013 PST files?",
    "LastUpdatedDate": "2014-10-19T16:32:02.77-07:00",
    "PlannedForRelease": "",
    "ReleaseVisibleToPublic": false,
    "Priority": {
      "Name": "Unassigned",
      "Severity": 0,
      "Id": 0
    },
    "ProjectName": "pstsdk",
    "ReportedDate": "2014-10-19T16:32:02.77-07:00",
    "Status": {
      "Name": "Proposed",
      "Id": 1
    },
    "ReasonClosed": {
      "Name": "Unassigned"
    },
    "Summary": "Problem in open Outlook 2010 PST file",
    "Type": {
      "Name": "Unassigned",
      "Id": 5
    },
    "VoteCount": 1,
    "Id": 10751
  },
  "FileAttachments": [],
  "Comments": []
}